fireproxify/__init__.py
fireproxify/cli.py
fireproxify/fireproxify.py
fireproxify-0.0.1.dist-info/entry_points.txt
fireproxify-0.0.1.dist-info/LICENSE
fireproxify-0.0.1.dist-info/WHEEL
fireproxify-0.0.1.dist-info/METADATA
fireproxify-0.0.1.dist-info/RECORD
