Metadata-Version: 2.1
Name: fireproxify
Version: 0.0.1
Summary: Fireprox as a package
Home-page: https://github.com/yok4i/fireproxify
Author: Mayk
Author-email: f7395296+yok4i@users.noreply.github.com
Requires-Python: >=3.8,<4.0
Classifier: Programming Language :: Python :: 3
Classifier: Programming Language :: Python :: 3.8
Classifier: Programming Language :: Python :: 3.9
Classifier: Programming Language :: Python :: 3.10
Requires-Dist: boto3 (>=1.26.50,<2.0.0)
Requires-Dist: bs4 (>=0.0.1,<0.0.2)
Requires-Dist: lxml (>=4.9.2,<5.0.0)
Requires-Dist: tldextract (>=3.4.0,<4.0.0)
Requires-Dist: tzlocal (>=4.2,<5.0)
Project-URL: Documentation, https://yok4i.github.io/fireproxify/
Project-URL: Repository, https://github.com/yok4i/fireproxify
